latex2ast/__init__.py
latex2ast/ast.py
latex2ast/lexer.py
latex2ast/parser.py
latex2ast/parsetab.py
latex2ast-0.0.1.dist-info/METADATA
latex2ast-0.0.1.dist-info/RECORD
latex2ast-0.0.1.dist-info/WHEEL
latex2ast-0.0.1.dist-info/top_level.txt
