Metadata-Version: 2.1
Name: latex2ast
Version: 0.0.1
Summary: A package for converter LaTeX equations to pseudo AST.
Home-page: https://github.com/blindtex/latex2ast/
Author: BlindTeX Team
Author-email: blindtexunal@gmail.com
License: UNKNOWN
Platform: UNKNOWN
Classifier: Programming Language :: Python :: 3
Classifier: License :: OSI Approved :: Apache Software License
Classifier: Operating System :: OS Independent
Requires-Dist: ply
